{"cameraMode":{"drawMode":0,"name":"Shaded","section":"Shading Mode"},"sceneLighting":true,"audioPlay":false,"sceneViewState":{"m_AlwaysRefresh":false,"showFog":true,"showSkybox":true,"showFlares":true,"showImageEffects":true,"showParticleSystems":true,"showVisualEffectGraphs":true,"m_FxEnabled":false},"in2DMode":false,"pivot":{"x":-14.42287826538086,"y":2.699118137359619,"z":8.72103500366211},"rotation":{"x":0.2699141502380371,"y":-0.6568725109100342,"z":0.2729543149471283,"w":0.6492960453033447},"size":18.65102195739746,"orthographic":false}